[
{
  "model": "auth.permission",
  "pk": 1,
  "fields": {
    "name": "Can add log entry",
    "content_type": 1,
    "codename": "add_logentry"
  }
},
{
  "model": "auth.permission",
  "pk": 2,
  "fields": {
    "name": "Can change log entry",
    "content_type": 1,
    "codename": "change_logentry"
  }
},
{
  "model": "auth.permission",
  "pk": 3,
  "fields": {
    "name": "Can delete log entry",
    "content_type": 1,
    "codename": "delete_logentry"
  }
},
{
  "model": "auth.permission",
  "pk": 4,
  "fields": {
    "name": "Can view log entry",
    "content_type": 1,
    "codename": "view_logentry"
  }
},
{
  "model": "auth.permission",
  "pk": 5,
  "fields": {
    "name": "Can add permission",
    "content_type": 2,
    "codename": "add_permission"
  }
},
{
  "model": "auth.permission",
  "pk": 6,
  "fields": {
    "name": "Can change permission",
    "content_type": 2,
    "codename": "change_permission"
  }
},
{
  "model": "auth.permission",
  "pk": 7,
  "fields": {
    "name": "Can delete permission",
    "content_type": 2,
    "codename": "delete_permission"
  }
},
{
  "model": "auth.permission",
  "pk": 8,
  "fields": {
    "name": "Can view permission",
    "content_type": 2,
    "codename": "view_permission"
  }
},
{
  "model": "auth.permission",
  "pk": 9,
  "fields": {
    "name": "Can add group",
    "content_type": 3,
    "codename": "add_group"
  }
},
{
  "model": "auth.permission",
  "pk": 10,
  "fields": {
    "name": "Can change group",
    "content_type": 3,
    "codename": "change_group"
  }
},
{
  "model": "auth.permission",
  "pk": 11,
  "fields": {
    "name": "Can delete group",
    "content_type": 3,
    "codename": "delete_group"
  }
},
{
  "model": "auth.permission",
  "pk": 12,
  "fields": {
    "name": "Can view group",
    "content_type": 3,
    "codename": "view_group"
  }
},
{
  "model": "auth.permission",
  "pk": 13,
  "fields": {
    "name": "Can add user",
    "content_type": 4,
    "codename": "add_user"
  }
},
{
  "model": "auth.permission",
  "pk": 14,
  "fields": {
    "name": "Can change user",
    "content_type": 4,
    "codename": "change_user"
  }
},
{
  "model": "auth.permission",
  "pk": 15,
  "fields": {
    "name": "Can delete user",
    "content_type": 4,
    "codename": "delete_user"
  }
},
{
  "model": "auth.permission",
  "pk": 16,
  "fields": {
    "name": "Can view user",
    "content_type": 4,
    "codename": "view_user"
  }
},
{
  "model": "auth.permission",
  "pk": 17,
  "fields": {
    "name": "Can add content type",
    "content_type": 5,
    "codename": "add_contenttype"
  }
},
{
  "model": "auth.permission",
  "pk": 18,
  "fields": {
    "name": "Can change content type",
    "content_type": 5,
    "codename": "change_contenttype"
  }
},
{
  "model": "auth.permission",
  "pk": 19,
  "fields": {
    "name": "Can delete content type",
    "content_type": 5,
    "codename": "delete_contenttype"
  }
},
{
  "model": "auth.permission",
  "pk": 20,
  "fields": {
    "name": "Can view content type",
    "content_type": 5,
    "codename": "view_contenttype"
  }
},
{
  "model": "auth.permission",
  "pk": 21,
  "fields": {
    "name": "Can add session",
    "content_type": 6,
    "codename": "add_session"
  }
},
{
  "model": "auth.permission",
  "pk": 22,
  "fields": {
    "name": "Can change session",
    "content_type": 6,
    "codename": "change_session"
  }
},
{
  "model": "auth.permission",
  "pk": 23,
  "fields": {
    "name": "Can delete session",
    "content_type": 6,
    "codename": "delete_session"
  }
},
{
  "model": "auth.permission",
  "pk": 24,
  "fields": {
    "name": "Can view session",
    "content_type": 6,
    "codename": "view_session"
  }
},
{
  "model": "auth.user",
  "pk": 24,
  "fields": {
    "password": "pbkdf2_sha256$320000$Rlw396H2Y11Xp1FzSzqDVg$xEXWU60vuaSjuBhGU8EwzgWL8MZj2S9ob2vYuKC8nFY=",
    "last_login": "2023-06-16T07:30:14.161Z",
    "is_superuser": true,
    "username": "admin",
    "first_name": "",
    "last_name": "",
    "email": "",
    "is_staff": true,
    "is_active": true,
    "date_joined": "2023-06-16T07:25:25.671Z",
    "groups": [],
    "user_permissions": []
  }
},
{
  "model": "auth.user",
  "pk": 27,
  "fields": {
    "password": "password123456",
    "last_login": null,
    "is_superuser": false,
    "username": "Juan",
    "first_name": "",
    "last_name": "",
    "email": "emailaddress@example.com",
    "is_staff": false,
    "is_active": true,
    "date_joined": "2023-06-16T08:07:18.685Z",
    "groups": [],
    "user_permissions": []
  }
},
{
  "model": "auth.user",
  "pk": 31,
  "fields": {
    "password": "K+4Ihz&!8(",
    "last_login": null,
    "is_superuser": false,
    "username": "Joshua Martinez",
    "first_name": "",
    "last_name": "",
    "email": "wfreeman@example.com",
    "is_staff": false,
    "is_active": true,
    "date_joined": "2023-06-16T12:29:05.523Z",
    "groups": [],
    "user_permissions": []
  }
},
{
  "model": "auth.user",
  "pk": 32,
  "fields": {
    "password": "04m(2WBbr%",
    "last_login": null,
    "is_superuser": false,
    "username": "Cynthia Hicks",
    "first_name": "",
    "last_name": "",
    "email": "morgan08@example.net",
    "is_staff": false,
    "is_active": true,
    "date_joined": "2023-06-16T12:29:05.523Z",
    "groups": [],
    "user_permissions": []
  }
},
{
  "model": "auth.user",
  "pk": 33,
  "fields": {
    "password": "Q00%BoPn*J",
    "last_login": null,
    "is_superuser": false,
    "username": "Roger Guzman",
    "first_name": "",
    "last_name": "",
    "email": "anthony91@example.net",
    "is_staff": false,
    "is_active": true,
    "date_joined": "2023-06-16T12:29:05.523Z",
    "groups": [],
    "user_permissions": []
  }
},
{
  "model": "auth.user",
  "pk": 34,
  "fields": {
    "password": "82*Xm3Sef4",
    "last_login": null,
    "is_superuser": false,
    "username": "Krista Barajas",
    "first_name": "",
    "last_name": "",
    "email": "evan63@example.org",
    "is_staff": false,
    "is_active": true,
    "date_joined": "2023-06-16T12:29:05.524Z",
    "groups": [],
    "user_permissions": []
  }
},
{
  "model": "auth.user",
  "pk": 35,
  "fields": {
    "password": "7AhI3Iu0#+",
    "last_login": null,
    "is_superuser": false,
    "username": "Edward King",
    "first_name": "",
    "last_name": "",
    "email": "ericabryan@example.net",
    "is_staff": false,
    "is_active": true,
    "date_joined": "2023-06-16T12:29:05.524Z",
    "groups": [],
    "user_permissions": []
  }
},
{
  "model": "auth.user",
  "pk": 36,
  "fields": {
    "password": "Zo1OAM#c%Q",
    "last_login": null,
    "is_superuser": false,
    "username": "Jennifer Malone",
    "first_name": "",
    "last_name": "",
    "email": "mhines@example.net",
    "is_staff": false,
    "is_active": true,
    "date_joined": "2023-06-16T12:30:03.770Z",
    "groups": [],
    "user_permissions": []
  }
},
{
  "model": "auth.user",
  "pk": 37,
  "fields": {
    "password": "O&g86ePtzq",
    "last_login": null,
    "is_superuser": false,
    "username": "Karina Bauer",
    "first_name": "",
    "last_name": "",
    "email": "jenniferjones@example.org",
    "is_staff": false,
    "is_active": true,
    "date_joined": "2023-06-16T12:30:03.770Z",
    "groups": [],
    "user_permissions": []
  }
},
{
  "model": "auth.user",
  "pk": 38,
  "fields": {
    "password": "43YNT3mq$B",
    "last_login": null,
    "is_superuser": false,
    "username": "Steven Davis",
    "first_name": "",
    "last_name": "",
    "email": "coreythompson@example.com",
    "is_staff": false,
    "is_active": true,
    "date_joined": "2023-06-16T12:30:03.771Z",
    "groups": [],
    "user_permissions": []
  }
},
{
  "model": "auth.user",
  "pk": 39,
  "fields": {
    "password": "&16EN3wmK5",
    "last_login": null,
    "is_superuser": false,
    "username": "Vanessa Phillips",
    "first_name": "",
    "last_name": "",
    "email": "bradleybutler@example.com",
    "is_staff": false,
    "is_active": true,
    "date_joined": "2023-06-16T12:30:03.771Z",
    "groups": [],
    "user_permissions": []
  }
},
{
  "model": "auth.user",
  "pk": 40,
  "fields": {
    "password": "&R8Kiu*zrl",
    "last_login": null,
    "is_superuser": false,
    "username": "Jessica Smith",
    "first_name": "",
    "last_name": "",
    "email": "christineharvey@example.org",
    "is_staff": false,
    "is_active": true,
    "date_joined": "2023-06-16T12:30:03.772Z",
    "groups": [],
    "user_permissions": []
  }
},
{
  "model": "auth.user",
  "pk": 41,
  "fields": {
    "password": "A9QrNH#n#4",
    "last_login": null,
    "is_superuser": false,
    "username": "Felicia Guerra",
    "first_name": "",
    "last_name": "",
    "email": "garciabrian@example.net",
    "is_staff": false,
    "is_active": true,
    "date_joined": "2023-06-16T12:30:03.772Z",
    "groups": [],
    "user_permissions": []
  }
},
{
  "model": "auth.user",
  "pk": 42,
  "fields": {
    "password": "+&&07Uce^L",
    "last_login": null,
    "is_superuser": false,
    "username": "Mitchell Wong",
    "first_name": "",
    "last_name": "",
    "email": "edward19@example.org",
    "is_staff": false,
    "is_active": true,
    "date_joined": "2023-06-16T12:30:03.772Z",
    "groups": [],
    "user_permissions": []
  }
},
{
  "model": "auth.user",
  "pk": 43,
  "fields": {
    "password": "V(n1SKafqk",
    "last_login": null,
    "is_superuser": false,
    "username": "Bonnie Stewart",
    "first_name": "",
    "last_name": "",
    "email": "crystalmelton@example.com",
    "is_staff": false,
    "is_active": true,
    "date_joined": "2023-06-16T12:30:03.773Z",
    "groups": [],
    "user_permissions": []
  }
},
{
  "model": "auth.user",
  "pk": 45,
  "fields": {
    "password": "g_b7NaCS6W",
    "last_login": null,
    "is_superuser": false,
    "username": "William Hill",
    "first_name": "",
    "last_name": "",
    "email": "chapmanmariah@example.org",
    "is_staff": false,
    "is_active": true,
    "date_joined": "2023-06-16T12:30:03.773Z",
    "groups": [],
    "user_permissions": []
  }
},
{
  "model": "auth.user",
  "pk": 46,
  "fields": {
    "password": "ZQPRidd)&6",
    "last_login": null,
    "is_superuser": false,
    "username": "Diane Patel",
    "first_name": "",
    "last_name": "",
    "email": "dcombs@example.com",
    "is_staff": false,
    "is_active": true,
    "date_joined": "2023-06-16T12:41:09.841Z",
    "groups": [],
    "user_permissions": []
  }
},
{
  "model": "auth.user",
  "pk": 47,
  "fields": {
    "password": ")1Dsj$o#7V",
    "last_login": null,
    "is_superuser": false,
    "username": "Timothy Ramos",
    "first_name": "",
    "last_name": "",
    "email": "asoto@example.org",
    "is_staff": false,
    "is_active": true,
    "date_joined": "2023-06-16T12:41:09.842Z",
    "groups": [],
    "user_permissions": []
  }
},
{
  "model": "auth.user",
  "pk": 48,
  "fields": {
    "password": "(Mmg4OmOU5",
    "last_login": null,
    "is_superuser": false,
    "username": "Crystal Mack",
    "first_name": "",
    "last_name": "",
    "email": "gonzalezemily@example.net",
    "is_staff": false,
    "is_active": true,
    "date_joined": "2023-06-16T12:41:09.842Z",
    "groups": [],
    "user_permissions": []
  }
},
{
  "model": "auth.user",
  "pk": 49,
  "fields": {
    "password": ")&5_Y+1nJH",
    "last_login": null,
    "is_superuser": false,
    "username": "Brian Hester",
    "first_name": "",
    "last_name": "",
    "email": "samanthaweaver@example.net",
    "is_staff": false,
    "is_active": true,
    "date_joined": "2023-06-16T12:41:09.842Z",
    "groups": [],
    "user_permissions": []
  }
},
{
  "model": "auth.user",
  "pk": 50,
  "fields": {
    "password": "1f9nEciF$$",
    "last_login": null,
    "is_superuser": false,
    "username": "Vanessa Alexander",
    "first_name": "",
    "last_name": "",
    "email": "acampbell@example.net",
    "is_staff": false,
    "is_active": true,
    "date_joined": "2023-06-16T12:41:09.843Z",
    "groups": [],
    "user_permissions": []
  }
},
{
  "model": "auth.user",
  "pk": 51,
  "fields": {
    "password": "%eMKdH3C81",
    "last_login": null,
    "is_superuser": false,
    "username": "Russell Miller",
    "first_name": "",
    "last_name": "",
    "email": "desireebrown@example.net",
    "is_staff": false,
    "is_active": true,
    "date_joined": "2023-06-16T12:41:09.843Z",
    "groups": [],
    "user_permissions": []
  }
},
{
  "model": "auth.user",
  "pk": 52,
  "fields": {
    "password": "^x7LO#pmex",
    "last_login": null,
    "is_superuser": false,
    "username": "Kaitlin Hunt",
    "first_name": "",
    "last_name": "",
    "email": "ramirezapril@example.org",
    "is_staff": false,
    "is_active": true,
    "date_joined": "2023-06-16T12:41:09.844Z",
    "groups": [],
    "user_permissions": []
  }
},
{
  "model": "auth.user",
  "pk": 53,
  "fields": {
    "password": "oR0ePc!sK+",
    "last_login": null,
    "is_superuser": false,
    "username": "Kevin Preston",
    "first_name": "",
    "last_name": "",
    "email": "kmartinez@example.com",
    "is_staff": false,
    "is_active": true,
    "date_joined": "2023-06-16T12:41:09.844Z",
    "groups": [],
    "user_permissions": []
  }
},
{
  "model": "auth.user",
  "pk": 54,
  "fields": {
    "password": "49WuYyev)3",
    "last_login": null,
    "is_superuser": false,
    "username": "Angela Payne",
    "first_name": "",
    "last_name": "",
    "email": "nelsondaniel@example.org",
    "is_staff": false,
    "is_active": true,
    "date_joined": "2023-06-16T12:41:09.844Z",
    "groups": [],
    "user_permissions": []
  }
},
{
  "model": "auth.user",
  "pk": 55,
  "fields": {
    "password": "Vn^9hPhtk7",
    "last_login": null,
    "is_superuser": false,
    "username": "Claudia Johnson",
    "first_name": "",
    "last_name": "",
    "email": "debracruz@example.org",
    "is_staff": false,
    "is_active": true,
    "date_joined": "2023-06-16T12:41:09.845Z",
    "groups": [],
    "user_permissions": []
  }
},
{
  "model": "auth.user",
  "pk": 56,
  "fields": {
    "password": "xh2Qpo*tg(",
    "last_login": null,
    "is_superuser": false,
    "username": "Ruth Ho",
    "first_name": "",
    "last_name": "",
    "email": "sheltonteresa@example.com",
    "is_staff": false,
    "is_active": true,
    "date_joined": "2023-06-16T12:44:08.162Z",
    "groups": [],
    "user_permissions": []
  }
},
{
  "model": "auth.user",
  "pk": 57,
  "fields": {
    "password": "++w1aOmaEf",
    "last_login": null,
    "is_superuser": false,
    "username": "Mr. Juan Dean MD",
    "first_name": "",
    "last_name": "",
    "email": "johnnymiller@example.com",
    "is_staff": false,
    "is_active": true,
    "date_joined": "2023-06-16T12:44:08.163Z",
    "groups": [],
    "user_permissions": []
  }
},
{
  "model": "auth.user",
  "pk": 58,
  "fields": {
    "password": "#zZrk^!0+7",
    "last_login": null,
    "is_superuser": false,
    "username": "Rodney Dawson",
    "first_name": "",
    "last_name": "",
    "email": "gwalker@example.com",
    "is_staff": false,
    "is_active": true,
    "date_joined": "2023-06-16T12:44:08.163Z",
    "groups": [],
    "user_permissions": []
  }
},
{
  "model": "auth.user",
  "pk": 59,
  "fields": {
    "password": "%Dox@1Gg7X",
    "last_login": null,
    "is_superuser": false,
    "username": "Madison Murray",
    "first_name": "",
    "last_name": "",
    "email": "gary44@example.com",
    "is_staff": false,
    "is_active": true,
    "date_joined": "2023-06-16T12:44:08.164Z",
    "groups": [],
    "user_permissions": []
  }
},
{
  "model": "auth.user",
  "pk": 60,
  "fields": {
    "password": "(5Beh(rEq_",
    "last_login": null,
    "is_superuser": false,
    "username": "Mrs. Michelle Herrera",
    "first_name": "",
    "last_name": "",
    "email": "usanchez@example.org",
    "is_staff": false,
    "is_active": true,
    "date_joined": "2023-06-16T12:44:08.164Z",
    "groups": [],
    "user_permissions": []
  }
},
{
  "model": "auth.user",
  "pk": 61,
  "fields": {
    "password": "$59IAvVM8p",
    "last_login": null,
    "is_superuser": false,
    "username": "Brandy Lambert",
    "first_name": "",
    "last_name": "",
    "email": "robin82@example.net",
    "is_staff": false,
    "is_active": true,
    "date_joined": "2023-06-16T12:44:08.164Z",
    "groups": [],
    "user_permissions": []
  }
},
{
  "model": "auth.user",
  "pk": 62,
  "fields": {
    "password": "_d86UTs+_F",
    "last_login": null,
    "is_superuser": false,
    "username": "Karen Bruce",
    "first_name": "",
    "last_name": "",
    "email": "amandaherring@example.net",
    "is_staff": false,
    "is_active": true,
    "date_joined": "2023-06-16T12:44:08.165Z",
    "groups": [],
    "user_permissions": []
  }
},
{
  "model": "auth.user",
  "pk": 63,
  "fields": {
    "password": "RJ1P5HPh!#",
    "last_login": null,
    "is_superuser": false,
    "username": "Bryan Williams",
    "first_name": "",
    "last_name": "",
    "email": "jeffreybennett@example.net",
    "is_staff": false,
    "is_active": true,
    "date_joined": "2023-06-16T12:44:08.165Z",
    "groups": [],
    "user_permissions": []
  }
},
{
  "model": "auth.user",
  "pk": 64,
  "fields": {
    "password": "@0GFyoGG&9",
    "last_login": null,
    "is_superuser": false,
    "username": "Elizabeth Jackson",
    "first_name": "",
    "last_name": "",
    "email": "michael90@example.org",
    "is_staff": false,
    "is_active": true,
    "date_joined": "2023-06-16T12:44:08.165Z",
    "groups": [],
    "user_permissions": []
  }
},
{
  "model": "auth.user",
  "pk": 65,
  "fields": {
    "password": "q4gA6NKu+w",
    "last_login": null,
    "is_superuser": false,
    "username": "Steve Cooper",
    "first_name": "",
    "last_name": "",
    "email": "bradley89@example.org",
    "is_staff": false,
    "is_active": true,
    "date_joined": "2023-06-16T12:44:08.166Z",
    "groups": [],
    "user_permissions": []
  }
},
{
  "model": "auth.user",
  "pk": 66,
  "fields": {
    "password": "9pFBcmdp%X",
    "last_login": null,
    "is_superuser": false,
    "username": "Deanna White",
    "first_name": "",
    "last_name": "",
    "email": "walkerjohnny@example.net",
    "is_staff": false,
    "is_active": true,
    "date_joined": "2023-06-16T12:46:21.683Z",
    "groups": [],
    "user_permissions": []
  }
},
{
  "model": "auth.user",
  "pk": 67,
  "fields": {
    "password": "^@9NXfS7Ed",
    "last_login": null,
    "is_superuser": false,
    "username": "Jeffrey Avila",
    "first_name": "",
    "last_name": "",
    "email": "wardshannon@example.org",
    "is_staff": false,
    "is_active": true,
    "date_joined": "2023-06-16T12:46:21.683Z",
    "groups": [],
    "user_permissions": []
  }
},
{
  "model": "auth.user",
  "pk": 68,
  "fields": {
    "password": "vw5F(dVh$C",
    "last_login": null,
    "is_superuser": false,
    "username": "Mr. Steven Rivera",
    "first_name": "",
    "last_name": "",
    "email": "hesteralexander@example.com",
    "is_staff": false,
    "is_active": true,
    "date_joined": "2023-06-16T12:46:21.684Z",
    "groups": [],
    "user_permissions": []
  }
},
{
  "model": "auth.user",
  "pk": 69,
  "fields": {
    "password": "7@4QcJ*z@8",
    "last_login": null,
    "is_superuser": false,
    "username": "Marcus Roberts",
    "first_name": "",
    "last_name": "",
    "email": "sullivankimberly@example.com",
    "is_staff": false,
    "is_active": true,
    "date_joined": "2023-06-16T12:46:21.684Z",
    "groups": [],
    "user_permissions": []
  }
},
{
  "model": "auth.user",
  "pk": 70,
  "fields": {
    "password": "8yuAt$*Q#4",
    "last_login": null,
    "is_superuser": false,
    "username": "Amanda Abbott",
    "first_name": "",
    "last_name": "",
    "email": "williamrivera@example.net",
    "is_staff": false,
    "is_active": true,
    "date_joined": "2023-06-16T12:46:21.684Z",
    "groups": [],
    "user_permissions": []
  }
},
{
  "model": "auth.user",
  "pk": 71,
  "fields": {
    "password": "#Ol)s+Bc*3",
    "last_login": null,
    "is_superuser": false,
    "username": "Joshua Jenkins",
    "first_name": "",
    "last_name": "",
    "email": "zsmith@example.net",
    "is_staff": false,
    "is_active": true,
    "date_joined": "2023-06-16T12:46:21.685Z",
    "groups": [],
    "user_permissions": []
  }
},
{
  "model": "auth.user",
  "pk": 72,
  "fields": {
    "password": "Fv4aSZDk^5",
    "last_login": null,
    "is_superuser": false,
    "username": "Brandon Sampson",
    "first_name": "",
    "last_name": "",
    "email": "wbutler@example.net",
    "is_staff": false,
    "is_active": true,
    "date_joined": "2023-06-16T12:46:21.685Z",
    "groups": [],
    "user_permissions": []
  }
},
{
  "model": "auth.user",
  "pk": 73,
  "fields": {
    "password": "^AFE8GiiDr",
    "last_login": null,
    "is_superuser": false,
    "username": "Luis Patel",
    "first_name": "",
    "last_name": "",
    "email": "joanne52@example.org",
    "is_staff": false,
    "is_active": true,
    "date_joined": "2023-06-16T12:46:21.685Z",
    "groups": [],
    "user_permissions": []
  }
},
{
  "model": "auth.user",
  "pk": 74,
  "fields": {
    "password": "I&7TmpMGs2",
    "last_login": null,
    "is_superuser": false,
    "username": "Cindy Higgins",
    "first_name": "",
    "last_name": "",
    "email": "acisneros@example.net",
    "is_staff": false,
    "is_active": true,
    "date_joined": "2023-06-16T12:46:38.613Z",
    "groups": [],
    "user_permissions": []
  }
},
{
  "model": "auth.user",
  "pk": 75,
  "fields": {
    "password": "@Y)Ihl%*D6",
    "last_login": null,
    "is_superuser": false,
    "username": "Joseph Gray",
    "first_name": "",
    "last_name": "",
    "email": "christian35@example.org",
    "is_staff": false,
    "is_active": true,
    "date_joined": "2023-06-16T12:46:38.614Z",
    "groups": [],
    "user_permissions": []
  }
},
{
  "model": "auth.user",
  "pk": 76,
  "fields": {
    "password": "T9G6D38c$#",
    "last_login": null,
    "is_superuser": false,
    "username": "Cory Jennings",
    "first_name": "",
    "last_name": "",
    "email": "cjordan@example.net",
    "is_staff": false,
    "is_active": true,
    "date_joined": "2023-06-16T12:46:38.614Z",
    "groups": [],
    "user_permissions": []
  }
},
{
  "model": "auth.user",
  "pk": 77,
  "fields": {
    "password": "T*4AZDKuV^",
    "last_login": null,
    "is_superuser": false,
    "username": "David Rogers",
    "first_name": "",
    "last_name": "",
    "email": "qmcdaniel@example.net",
    "is_staff": false,
    "is_active": true,
    "date_joined": "2023-06-16T12:46:38.614Z",
    "groups": [],
    "user_permissions": []
  }
},
{
  "model": "auth.user",
  "pk": 78,
  "fields": {
    "password": "X+5qRXGao*",
    "last_login": null,
    "is_superuser": false,
    "username": "David Esparza",
    "first_name": "",
    "last_name": "",
    "email": "chenrodney@example.org",
    "is_staff": false,
    "is_active": true,
    "date_joined": "2023-06-16T12:46:38.615Z",
    "groups": [],
    "user_permissions": []
  }
},
{
  "model": "auth.user",
  "pk": 79,
  "fields": {
    "password": "%8dOW&mjAd",
    "last_login": null,
    "is_superuser": false,
    "username": "Deanna Rowe",
    "first_name": "",
    "last_name": "",
    "email": "juan64@example.com",
    "is_staff": false,
    "is_active": true,
    "date_joined": "2023-06-16T12:46:38.615Z",
    "groups": [],
    "user_permissions": []
  }
},
{
  "model": "auth.user",
  "pk": 80,
  "fields": {
    "password": "%0Leacng05",
    "last_login": null,
    "is_superuser": false,
    "username": "Kerry Reed",
    "first_name": "",
    "last_name": "",
    "email": "charles98@example.net",
    "is_staff": false,
    "is_active": true,
    "date_joined": "2023-06-16T12:46:38.616Z",
    "groups": [],
    "user_permissions": []
  }
},
{
  "model": "auth.user",
  "pk": 81,
  "fields": {
    "password": "@2QBk6ts43",
    "last_login": null,
    "is_superuser": false,
    "username": "Hector Lee",
    "first_name": "",
    "last_name": "",
    "email": "lori76@example.net",
    "is_staff": false,
    "is_active": true,
    "date_joined": "2023-06-16T12:46:38.616Z",
    "groups": [],
    "user_permissions": []
  }
},
{
  "model": "auth.user",
  "pk": 82,
  "fields": {
    "password": "i9Y#nCS4*t",
    "last_login": null,
    "is_superuser": false,
    "username": "Kelly Brown",
    "first_name": "",
    "last_name": "",
    "email": "wgregory@example.org",
    "is_staff": false,
    "is_active": true,
    "date_joined": "2023-06-16T12:52:39.047Z",
    "groups": [],
    "user_permissions": []
  }
},
{
  "model": "auth.user",
  "pk": 83,
  "fields": {
    "password": "GX9P#LQi_E",
    "last_login": null,
    "is_superuser": false,
    "username": "Dwayne Woods",
    "first_name": "",
    "last_name": "",
    "email": "zphillips@example.net",
    "is_staff": false,
    "is_active": true,
    "date_joined": "2023-06-16T12:53:53.506Z",
    "groups": [],
    "user_permissions": []
  }
},
{
  "model": "auth.user",
  "pk": 84,
  "fields": {
    "password": "%Fr06ASgd3",
    "last_login": null,
    "is_superuser": false,
    "username": "Mr. Cameron Joseph",
    "first_name": "",
    "last_name": "",
    "email": "martinezmelvin@example.org",
    "is_staff": false,
    "is_active": true,
    "date_joined": "2023-06-16T12:55:06.289Z",
    "groups": [],
    "user_permissions": []
  }
},
{
  "model": "auth.user",
  "pk": 85,
  "fields": {
    "password": "8^+pc1#rRQ",
    "last_login": null,
    "is_superuser": false,
    "username": "Jessica Bradley",
    "first_name": "",
    "last_name": "",
    "email": "joseph21@example.com",
    "is_staff": false,
    "is_active": true,
    "date_joined": "2023-06-16T13:05:29.759Z",
    "groups": [],
    "user_permissions": []
  }
},
{
  "model": "auth.user",
  "pk": 86,
  "fields": {
    "password": "8gYiGyga^b",
    "last_login": null,
    "is_superuser": false,
    "username": "Kenneth Smith",
    "first_name": "",
    "last_name": "",
    "email": "odixon@example.org",
    "is_staff": false,
    "is_active": true,
    "date_joined": "2023-06-16T13:10:56.652Z",
    "groups": [],
    "user_permissions": []
  }
},
{
  "model": "auth.user",
  "pk": 87,
  "fields": {
    "password": "*2gMQ8yM+r",
    "last_login": null,
    "is_superuser": false,
    "username": "Danielle Watkins",
    "first_name": "",
    "last_name": "",
    "email": "chambersfrances@example.com",
    "is_staff": false,
    "is_active": true,
    "date_joined": "2023-06-16T13:15:19.063Z",
    "groups": [],
    "user_permissions": []
  }
},
{
  "model": "auth.user",
  "pk": 88,
  "fields": {
    "password": "(0Q(NjMRet",
    "last_login": null,
    "is_superuser": false,
    "username": "Crystal Harding",
    "first_name": "",
    "last_name": "",
    "email": "reneebenson@example.org",
    "is_staff": false,
    "is_active": true,
    "date_joined": "2023-06-16T13:19:36.319Z",
    "groups": [],
    "user_permissions": []
  }
},
{
  "model": "auth.user",
  "pk": 89,
  "fields": {
    "password": "9N_FwNp6$g",
    "last_login": null,
    "is_superuser": false,
    "username": "Kevin Holmes",
    "first_name": "",
    "last_name": "",
    "email": "courtney03@example.org",
    "is_staff": false,
    "is_active": true,
    "date_joined": "2023-06-16T13:26:58.700Z",
    "groups": [],
    "user_permissions": []
  }
},
{
  "model": "auth.user",
  "pk": 90,
  "fields": {
    "password": "a!9QBk2pm#",
    "last_login": null,
    "is_superuser": false,
    "username": "Matthew Castaneda",
    "first_name": "",
    "last_name": "",
    "email": "kelleyfelicia@example.org",
    "is_staff": false,
    "is_active": true,
    "date_joined": "2023-06-16T13:27:23.068Z",
    "groups": [],
    "user_permissions": []
  }
},
{
  "model": "auth.user",
  "pk": 91,
  "fields": {
    "password": "+0TjW6Deg4",
    "last_login": null,
    "is_superuser": false,
    "username": "Mrs. Kayla Beard",
    "first_name": "",
    "last_name": "",
    "email": "ogreen@example.org",
    "is_staff": false,
    "is_active": true,
    "date_joined": "2023-06-16T13:27:48.920Z",
    "groups": [],
    "user_permissions": []
  }
},
{
  "model": "auth.user",
  "pk": 92,
  "fields": {
    "password": "wK8Y^_ex*&",
    "last_login": null,
    "is_superuser": false,
    "username": "Tanya Wilson",
    "first_name": "",
    "last_name": "",
    "email": "kglenn@example.com",
    "is_staff": false,
    "is_active": true,
    "date_joined": "2023-06-16T13:28:11.931Z",
    "groups": [],
    "user_permissions": []
  }
},
{
  "model": "auth.user",
  "pk": 93,
  "fields": {
    "password": "_n!9L+DfzX",
    "last_login": null,
    "is_superuser": false,
    "username": "Nathan Gentry",
    "first_name": "",
    "last_name": "",
    "email": "yhinton@example.com",
    "is_staff": false,
    "is_active": true,
    "date_joined": "2023-06-16T13:35:45.618Z",
    "groups": [],
    "user_permissions": []
  }
},
{
  "model": "auth.user",
  "pk": 94,
  "fields": {
    "password": "!V3@Fuoqag",
    "last_login": null,
    "is_superuser": false,
    "username": "Ryan Martinez",
    "first_name": "",
    "last_name": "",
    "email": "frankjohnson@example.com",
    "is_staff": false,
    "is_active": true,
    "date_joined": "2023-06-16T13:46:53.820Z",
    "groups": [],
    "user_permissions": []
  }
},
{
  "model": "auth.user",
  "pk": 95,
  "fields": {
    "password": "J$(k0YDb4A",
    "last_login": null,
    "is_superuser": false,
    "username": "Roberta Mckay",
    "first_name": "",
    "last_name": "",
    "email": "nancysmith@example.org",
    "is_staff": false,
    "is_active": true,
    "date_joined": "2023-06-16T13:49:33.718Z",
    "groups": [],
    "user_permissions": []
  }
},
{
  "model": "auth.user",
  "pk": 96,
  "fields": {
    "password": "O!T^7WzmQ)",
    "last_login": null,
    "is_superuser": false,
    "username": "Joshua Freeman",
    "first_name": "",
    "last_name": "",
    "email": "yclark@example.org",
    "is_staff": false,
    "is_active": true,
    "date_joined": "2023-06-16T13:49:33.719Z",
    "groups": [],
    "user_permissions": []
  }
},
{
  "model": "auth.user",
  "pk": 97,
  "fields": {
    "password": "%$To_NaR59",
    "last_login": null,
    "is_superuser": false,
    "username": "Matthew Moss",
    "first_name": "",
    "last_name": "",
    "email": "munozvictoria@example.net",
    "is_staff": false,
    "is_active": true,
    "date_joined": "2023-06-16T13:49:33.719Z",
    "groups": [],
    "user_permissions": []
  }
},
{
  "model": "auth.user",
  "pk": 98,
  "fields": {
    "password": "ykT%LZqf@7",
    "last_login": null,
    "is_superuser": false,
    "username": "Lee Kirk",
    "first_name": "",
    "last_name": "",
    "email": "natalie65@example.net",
    "is_staff": false,
    "is_active": true,
    "date_joined": "2023-06-16T13:49:33.719Z",
    "groups": [],
    "user_permissions": []
  }
},
{
  "model": "auth.user",
  "pk": 99,
  "fields": {
    "password": "!O1KSNY6k4",
    "last_login": null,
    "is_superuser": false,
    "username": "Richard Rowe",
    "first_name": "",
    "last_name": "",
    "email": "garciajennifer@example.com",
    "is_staff": false,
    "is_active": true,
    "date_joined": "2023-06-16T13:49:33.720Z",
    "groups": [],
    "user_permissions": []
  }
},
{
  "model": "auth.user",
  "pk": 100,
  "fields": {
    "password": "^7^OPjwE*1",
    "last_login": null,
    "is_superuser": false,
    "username": "Austin Wang",
    "first_name": "",
    "last_name": "",
    "email": "louisroberts@example.net",
    "is_staff": false,
    "is_active": true,
    "date_joined": "2023-06-16T13:54:10.339Z",
    "groups": [],
    "user_permissions": []
  }
},
{
  "model": "auth.user",
  "pk": 101,
  "fields": {
    "password": "^leKq!kMH4",
    "last_login": null,
    "is_superuser": false,
    "username": "Danielle Wright",
    "first_name": "",
    "last_name": "",
    "email": "idean@example.org",
    "is_staff": false,
    "is_active": true,
    "date_joined": "2023-06-16T13:54:10.339Z",
    "groups": [],
    "user_permissions": []
  }
},
{
  "model": "auth.user",
  "pk": 102,
  "fields": {
    "password": "@2mFCha+qI",
    "last_login": null,
    "is_superuser": false,
    "username": "Adam Clark",
    "first_name": "",
    "last_name": "",
    "email": "mruiz@example.com",
    "is_staff": false,
    "is_active": true,
    "date_joined": "2023-06-16T13:54:10.339Z",
    "groups": [],
    "user_permissions": []
  }
},
{
  "model": "auth.user",
  "pk": 103,
  "fields": {
    "password": "&PM7D6Iy+*",
    "last_login": null,
    "is_superuser": false,
    "username": "Dan Allen",
    "first_name": "",
    "last_name": "",
    "email": "millergary@example.com",
    "is_staff": false,
    "is_active": true,
    "date_joined": "2023-06-16T13:54:10.340Z",
    "groups": [],
    "user_permissions": []
  }
},
{
  "model": "auth.user",
  "pk": 104,
  "fields": {
    "password": "i8R#DC$p$Z",
    "last_login": null,
    "is_superuser": false,
    "username": "Richard Burton",
    "first_name": "",
    "last_name": "",
    "email": "ramireztammy@example.com",
    "is_staff": false,
    "is_active": true,
    "date_joined": "2023-06-16T13:54:10.340Z",
    "groups": [],
    "user_permissions": []
  }
},
{
  "model": "auth.user",
  "pk": 105,
  "fields": {
    "password": ")!0C1r6%CE",
    "last_login": null,
    "is_superuser": false,
    "username": "Tracie Myers",
    "first_name": "",
    "last_name": "",
    "email": "amanda16@example.org",
    "is_staff": false,
    "is_active": true,
    "date_joined": "2023-06-16T13:55:52.675Z",
    "groups": [],
    "user_permissions": []
  }
},
{
  "model": "auth.user",
  "pk": 106,
  "fields": {
    "password": "Z7LYR2kj^H",
    "last_login": null,
    "is_superuser": false,
    "username": "Tony Page",
    "first_name": "",
    "last_name": "",
    "email": "ktran@example.net",
    "is_staff": false,
    "is_active": true,
    "date_joined": "2023-06-16T13:55:52.675Z",
    "groups": [],
    "user_permissions": []
  }
},
{
  "model": "auth.user",
  "pk": 107,
  "fields": {
    "password": ")y2RsXYU&0",
    "last_login": null,
    "is_superuser": false,
    "username": "Lauren Sloan",
    "first_name": "",
    "last_name": "",
    "email": "sgood@example.org",
    "is_staff": false,
    "is_active": true,
    "date_joined": "2023-06-16T13:55:52.676Z",
    "groups": [],
    "user_permissions": []
  }
},
{
  "model": "auth.user",
  "pk": 108,
  "fields": {
    "password": "H@Z5Y6Lxim",
    "last_login": null,
    "is_superuser": false,
    "username": "Damon Allison",
    "first_name": "",
    "last_name": "",
    "email": "raymondsmith@example.org",
    "is_staff": false,
    "is_active": true,
    "date_joined": "2023-06-16T13:55:52.676Z",
    "groups": [],
    "user_permissions": []
  }
},
{
  "model": "auth.user",
  "pk": 109,
  "fields": {
    "password": "I&5BRdvurr",
    "last_login": null,
    "is_superuser": false,
    "username": "Leroy Brown",
    "first_name": "",
    "last_name": "",
    "email": "nataliethompson@example.net",
    "is_staff": false,
    "is_active": true,
    "date_joined": "2023-06-16T13:55:52.676Z",
    "groups": [],
    "user_permissions": []
  }
},
{
  "model": "auth.user",
  "pk": 110,
  "fields": {
    "password": "i!&38pTpbx",
    "last_login": null,
    "is_superuser": false,
    "username": "Natalie Rogers",
    "first_name": "",
    "last_name": "",
    "email": "stokesnancy@example.net",
    "is_staff": false,
    "is_active": true,
    "date_joined": "2023-06-16T14:03:39.873Z",
    "groups": [],
    "user_permissions": []
  }
},
{
  "model": "auth.user",
  "pk": 111,
  "fields": {
    "password": "v+N6HgMIg$",
    "last_login": null,
    "is_superuser": false,
    "username": "Kathryn Cole",
    "first_name": "",
    "last_name": "",
    "email": "karenwise@example.net",
    "is_staff": false,
    "is_active": true,
    "date_joined": "2023-06-16T14:03:39.873Z",
    "groups": [],
    "user_permissions": []
  }
},
{
  "model": "auth.user",
  "pk": 112,
  "fields": {
    "password": "@#_T0aIsFi",
    "last_login": null,
    "is_superuser": false,
    "username": "Patricia Meadows DVM",
    "first_name": "",
    "last_name": "",
    "email": "blankenshipjeanette@example.org",
    "is_staff": false,
    "is_active": true,
    "date_joined": "2023-06-16T14:04:01.876Z",
    "groups": [],
    "user_permissions": []
  }
},
{
  "model": "auth.user",
  "pk": 113,
  "fields": {
    "password": "3$2Grggk8E",
    "last_login": null,
    "is_superuser": false,
    "username": "Jordan Duncan",
    "first_name": "",
    "last_name": "",
    "email": "mary26@example.net",
    "is_staff": false,
    "is_active": true,
    "date_joined": "2023-06-16T14:04:01.876Z",
    "groups": [],
    "user_permissions": []
  }
},
{
  "model": "auth.user",
  "pk": 114,
  "fields": {
    "password": "_5^PADr(Ub",
    "last_login": null,
    "is_superuser": false,
    "username": "Kayla Stevens",
    "first_name": "",
    "last_name": "",
    "email": "rfletcher@example.org",
    "is_staff": false,
    "is_active": true,
    "date_joined": "2023-06-16T14:04:13.442Z",
    "groups": [],
    "user_permissions": []
  }
},
{
  "model": "auth.user",
  "pk": 115,
  "fields": {
    "password": "Sva+L23x#9",
    "last_login": null,
    "is_superuser": false,
    "username": "Jared Hammond",
    "first_name": "",
    "last_name": "",
    "email": "sethfields@example.org",
    "is_staff": false,
    "is_active": true,
    "date_joined": "2023-06-16T14:04:13.443Z",
    "groups": [],
    "user_permissions": []
  }
},
{
  "model": "auth.user",
  "pk": 116,
  "fields": {
    "password": "zhG^+8PcQq",
    "last_login": null,
    "is_superuser": false,
    "username": "Jeffrey Mahoney",
    "first_name": "",
    "last_name": "",
    "email": "dsingleton@example.org",
    "is_staff": false,
    "is_active": true,
    "date_joined": "2023-06-16T14:04:30.419Z",
    "groups": [],
    "user_permissions": []
  }
},
{
  "model": "auth.user",
  "pk": 117,
  "fields": {
    "password": "$**7YTTl79",
    "last_login": null,
    "is_superuser": false,
    "username": "Elizabeth Smith",
    "first_name": "",
    "last_name": "",
    "email": "gthompson@example.com",
    "is_staff": false,
    "is_active": true,
    "date_joined": "2023-06-16T14:04:30.419Z",
    "groups": [],
    "user_permissions": []
  }
},
{
  "model": "auth.user",
  "pk": 118,
  "fields": {
    "password": "*L6IejM6iY",
    "last_login": null,
    "is_superuser": false,
    "username": "Brian Day",
    "first_name": "",
    "last_name": "",
    "email": "serranomichael@example.com",
    "is_staff": false,
    "is_active": true,
    "date_joined": "2023-06-16T14:04:30.420Z",
    "groups": [],
    "user_permissions": []
  }
},
{
  "model": "auth.user",
  "pk": 119,
  "fields": {
    "password": "Z3#K85tl%+",
    "last_login": null,
    "is_superuser": false,
    "username": "Lisa Salazar",
    "first_name": "",
    "last_name": "",
    "email": "robert24@example.com",
    "is_staff": false,
    "is_active": true,
    "date_joined": "2023-06-16T14:04:30.420Z",
    "groups": [],
    "user_permissions": []
  }
},
{
  "model": "auth.user",
  "pk": 120,
  "fields": {
    "password": "$7LyKL#oXh",
    "last_login": null,
    "is_superuser": false,
    "username": "Sarah Howell",
    "first_name": "",
    "last_name": "",
    "email": "frodriguez@example.net",
    "is_staff": false,
    "is_active": true,
    "date_joined": "2023-06-16T14:04:44.062Z",
    "groups": [],
    "user_permissions": []
  }
},
{
  "model": "auth.user",
  "pk": 121,
  "fields": {
    "password": "^C9Dtv47Ft",
    "last_login": null,
    "is_superuser": false,
    "username": "Carrie Werner",
    "first_name": "",
    "last_name": "",
    "email": "jacquelineharris@example.net",
    "is_staff": false,
    "is_active": true,
    "date_joined": "2023-06-16T14:04:44.062Z",
    "groups": [],
    "user_permissions": []
  }
},
{
  "model": "auth.user",
  "pk": 122,
  "fields": {
    "password": "C6fRg#VH@6",
    "last_login": null,
    "is_superuser": false,
    "username": "Donna Barber",
    "first_name": "",
    "last_name": "",
    "email": "danielbrown@example.net",
    "is_staff": false,
    "is_active": true,
    "date_joined": "2023-06-16T14:04:44.063Z",
    "groups": [],
    "user_permissions": []
  }
},
{
  "model": "auth.user",
  "pk": 123,
  "fields": {
    "password": "2C#i31Qg%$",
    "last_login": null,
    "is_superuser": false,
    "username": "Andrea Haynes",
    "first_name": "",
    "last_name": "",
    "email": "tduke@example.net",
    "is_staff": false,
    "is_active": true,
    "date_joined": "2023-06-16T14:04:44.063Z",
    "groups": [],
    "user_permissions": []
  }
},
{
  "model": "auth.user",
  "pk": 124,
  "fields": {
    "password": "2iHsTQy1^y",
    "last_login": null,
    "is_superuser": false,
    "username": "Thomas Fry",
    "first_name": "",
    "last_name": "",
    "email": "heather52@example.org",
    "is_staff": false,
    "is_active": true,
    "date_joined": "2023-06-16T14:04:44.064Z",
    "groups": [],
    "user_permissions": []
  }
},
{
  "model": "auth.user",
  "pk": 125,
  "fields": {
    "password": "&aG@!0VnhW",
    "last_login": null,
    "is_superuser": false,
    "username": "Mario Garcia",
    "first_name": "",
    "last_name": "",
    "email": "redwards@example.org",
    "is_staff": false,
    "is_active": true,
    "date_joined": "2023-06-16T14:05:52.222Z",
    "groups": [],
    "user_permissions": []
  }
},
{
  "model": "auth.user",
  "pk": 126,
  "fields": {
    "password": "^x6gvIAjs^",
    "last_login": null,
    "is_superuser": false,
    "username": "Jose Hobbs",
    "first_name": "",
    "last_name": "",
    "email": "bellmarc@example.com",
    "is_staff": false,
    "is_active": true,
    "date_joined": "2023-06-16T14:05:52.222Z",
    "groups": [],
    "user_permissions": []
  }
},
{
  "model": "auth.user",
  "pk": 127,
  "fields": {
    "password": "@d13Cvk*kX",
    "last_login": null,
    "is_superuser": false,
    "username": "Jessica Ali",
    "first_name": "",
    "last_name": "",
    "email": "turneranthony@example.com",
    "is_staff": false,
    "is_active": true,
    "date_joined": "2023-06-16T14:05:52.223Z",
    "groups": [],
    "user_permissions": []
  }
},
{
  "model": "auth.user",
  "pk": 128,
  "fields": {
    "password": "nDN4EyJl!&",
    "last_login": null,
    "is_superuser": false,
    "username": "Samantha Brown",
    "first_name": "",
    "last_name": "",
    "email": "clintonjames@example.com",
    "is_staff": false,
    "is_active": true,
    "date_joined": "2023-06-16T14:05:52.223Z",
    "groups": [],
    "user_permissions": []
  }
},
{
  "model": "auth.user",
  "pk": 129,
  "fields": {
    "password": "Zqs(4DNlHf",
    "last_login": null,
    "is_superuser": false,
    "username": "Wesley Clark",
    "first_name": "",
    "last_name": "",
    "email": "andrewrodriguez@example.com",
    "is_staff": false,
    "is_active": true,
    "date_joined": "2023-06-16T14:06:51.148Z",
    "groups": [],
    "user_permissions": []
  }
},
{
  "model": "auth.user",
  "pk": 130,
  "fields": {
    "password": "W)4Umva7&R",
    "last_login": null,
    "is_superuser": false,
    "username": "Amanda Sullivan",
    "first_name": "",
    "last_name": "",
    "email": "gregorymartinez@example.net",
    "is_staff": false,
    "is_active": true,
    "date_joined": "2023-06-16T14:06:51.149Z",
    "groups": [],
    "user_permissions": []
  }
},
{
  "model": "auth.user",
  "pk": 131,
  "fields": {
    "password": "!4JqPXCzbc",
    "last_login": null,
    "is_superuser": false,
    "username": "Deborah Ward",
    "first_name": "",
    "last_name": "",
    "email": "nreid@example.org",
    "is_staff": false,
    "is_active": true,
    "date_joined": "2023-06-16T14:06:51.149Z",
    "groups": [],
    "user_permissions": []
  }
},
{
  "model": "auth.user",
  "pk": 132,
  "fields": {
    "password": "%1b5DvldPu",
    "last_login": null,
    "is_superuser": false,
    "username": "Jeffrey Rodriguez",
    "first_name": "",
    "last_name": "",
    "email": "schwartzstephen@example.net",
    "is_staff": false,
    "is_active": true,
    "date_joined": "2023-06-16T14:06:51.149Z",
    "groups": [],
    "user_permissions": []
  }
},
{
  "model": "auth.user",
  "pk": 133,
  "fields": {
    "password": "fz2QQ1ef#7",
    "last_login": null,
    "is_superuser": false,
    "username": "Ronald Fletcher",
    "first_name": "",
    "last_name": "",
    "email": "michael20@example.net",
    "is_staff": false,
    "is_active": true,
    "date_joined": "2023-06-16T14:07:30.087Z",
    "groups": [],
    "user_permissions": []
  }
},
{
  "model": "auth.user",
  "pk": 134,
  "fields": {
    "password": "D2@0TRap%5",
    "last_login": null,
    "is_superuser": false,
    "username": "Mary West",
    "first_name": "",
    "last_name": "",
    "email": "branchmatthew@example.com",
    "is_staff": false,
    "is_active": true,
    "date_joined": "2023-06-16T14:07:30.087Z",
    "groups": [],
    "user_permissions": []
  }
},
{
  "model": "auth.user",
  "pk": 135,
  "fields": {
    "password": "&1I2AXayw_",
    "last_login": null,
    "is_superuser": false,
    "username": "Courtney Cook",
    "first_name": "",
    "last_name": "",
    "email": "scotteileen@example.net",
    "is_staff": false,
    "is_active": true,
    "date_joined": "2023-06-16T14:07:30.088Z",
    "groups": [],
    "user_permissions": []
  }
},
{
  "model": "auth.user",
  "pk": 136,
  "fields": {
    "password": "$9*JXGCcpg",
    "last_login": null,
    "is_superuser": false,
    "username": "Stephanie Ferguson",
    "first_name": "",
    "last_name": "",
    "email": "christiancooper@example.org",
    "is_staff": false,
    "is_active": true,
    "date_joined": "2023-06-16T14:07:30.088Z",
    "groups": [],
    "user_permissions": []
  }
},
{
  "model": "auth.user",
  "pk": 137,
  "fields": {
    "password": "@&QxKSh!!7",
    "last_login": null,
    "is_superuser": false,
    "username": "Jesse Sanders",
    "first_name": "",
    "last_name": "",
    "email": "uhernandez@example.com",
    "is_staff": false,
    "is_active": true,
    "date_joined": "2023-06-16T14:07:44.733Z",
    "groups": [],
    "user_permissions": []
  }
},
{
  "model": "auth.user",
  "pk": 138,
  "fields": {
    "password": "2gP8UU5gb&",
    "last_login": null,
    "is_superuser": false,
    "username": "Tammy Coleman",
    "first_name": "",
    "last_name": "",
    "email": "dstone@example.com",
    "is_staff": false,
    "is_active": true,
    "date_joined": "2023-06-16T14:07:44.734Z",
    "groups": [],
    "user_permissions": []
  }
},
{
  "model": "auth.user",
  "pk": 139,
  "fields": {
    "password": "%P3Ktqc^v$",
    "last_login": null,
    "is_superuser": false,
    "username": "Cynthia Day",
    "first_name": "",
    "last_name": "",
    "email": "mary95@example.com",
    "is_staff": false,
    "is_active": true,
    "date_joined": "2023-06-16T14:07:44.734Z",
    "groups": [],
    "user_permissions": []
  }
},
{
  "model": "auth.user",
  "pk": 140,
  "fields": {
    "password": "eQK9QyPp%4",
    "last_login": null,
    "is_superuser": false,
    "username": "Jessica Evans",
    "first_name": "",
    "last_name": "",
    "email": "kimberly50@example.org",
    "is_staff": false,
    "is_active": true,
    "date_joined": "2023-06-16T14:07:44.735Z",
    "groups": [],
    "user_permissions": []
  }
},
{
  "model": "auth.user",
  "pk": 141,
  "fields": {
    "password": "8kA1N#Gm$d",
    "last_login": null,
    "is_superuser": false,
    "username": "Cynthia Smith",
    "first_name": "",
    "last_name": "",
    "email": "mariamurphy@example.org",
    "is_staff": false,
    "is_active": true,
    "date_joined": "2023-06-16T14:07:44.735Z",
    "groups": [],
    "user_permissions": []
  }
},
{
  "model": "auth.user",
  "pk": 142,
  "fields": {
    "password": "M_3mG4ytbp",
    "last_login": null,
    "is_superuser": false,
    "username": "Samantha Williams",
    "first_name": "",
    "last_name": "",
    "email": "penatonya@example.net",
    "is_staff": false,
    "is_active": true,
    "date_joined": "2023-06-16T14:07:44.735Z",
    "groups": [],
    "user_permissions": []
  }
},
{
  "model": "auth.user",
  "pk": 143,
  "fields": {
    "password": "@_E#L@b+m6",
    "last_login": null,
    "is_superuser": false,
    "username": "Pamela Jones",
    "first_name": "",
    "last_name": "",
    "email": "jacobsoto@example.com",
    "is_staff": false,
    "is_active": true,
    "date_joined": "2023-06-16T14:07:44.736Z",
    "groups": [],
    "user_permissions": []
  }
},
{
  "model": "auth.user",
  "pk": 144,
  "fields": {
    "password": "cm@CF5Oswp",
    "last_login": null,
    "is_superuser": false,
    "username": "Randy Mendoza",
    "first_name": "",
    "last_name": "",
    "email": "wrightkenneth@example.org",
    "is_staff": false,
    "is_active": true,
    "date_joined": "2023-06-16T14:07:44.736Z",
    "groups": [],
    "user_permissions": []
  }
},
{
  "model": "auth.user",
  "pk": 145,
  "fields": {
    "password": "W!4djMn0+X",
    "last_login": null,
    "is_superuser": false,
    "username": "Michael Castro",
    "first_name": "",
    "last_name": "",
    "email": "alanfaulkner@example.net",
    "is_staff": false,
    "is_active": true,
    "date_joined": "2023-06-16T14:07:44.737Z",
    "groups": [],
    "user_permissions": []
  }
},
{
  "model": "auth.user",
  "pk": 146,
  "fields": {
    "password": "!0_jTf_6jr",
    "last_login": null,
    "is_superuser": false,
    "username": "Andrea Solomon",
    "first_name": "",
    "last_name": "",
    "email": "krista56@example.org",
    "is_staff": false,
    "is_active": true,
    "date_joined": "2023-06-16T14:08:42.756Z",
    "groups": [],
    "user_permissions": []
  }
},
{
  "model": "auth.user",
  "pk": 147,
  "fields": {
    "password": "L^1xV4iAkZ",
    "last_login": null,
    "is_superuser": false,
    "username": "Michael Dixon",
    "first_name": "",
    "last_name": "",
    "email": "hillelizabeth@example.org",
    "is_staff": false,
    "is_active": true,
    "date_joined": "2023-06-16T14:09:54.418Z",
    "groups": [],
    "user_permissions": []
  }
},
{
  "model": "auth.user",
  "pk": 148,
  "fields": {
    "password": ")N5qIAwbLd",
    "last_login": null,
    "is_superuser": false,
    "username": "Trevor Roberts",
    "first_name": "",
    "last_name": "",
    "email": "hayessean@example.org",
    "is_staff": false,
    "is_active": true,
    "date_joined": "2023-06-16T14:09:54.418Z",
    "groups": [],
    "user_permissions": []
  }
},
{
  "model": "auth.user",
  "pk": 149,
  "fields": {
    "password": "+X0XZR0q7p",
    "last_login": null,
    "is_superuser": false,
    "username": "Stacey Grimes",
    "first_name": "",
    "last_name": "",
    "email": "gregory51@example.net",
    "is_staff": false,
    "is_active": true,
    "date_joined": "2023-06-16T14:09:54.419Z",
    "groups": [],
    "user_permissions": []
  }
},
{
  "model": "auth.user",
  "pk": 150,
  "fields": {
    "password": "Xj0@@!Bc*8",
    "last_login": null,
    "is_superuser": false,
    "username": "Martin Hernandez",
    "first_name": "",
    "last_name": "",
    "email": "kingdavid@example.com",
    "is_staff": false,
    "is_active": true,
    "date_joined": "2023-06-16T14:11:43.294Z",
    "groups": [],
    "user_permissions": []
  }
},
{
  "model": "auth.user",
  "pk": 151,
  "fields": {
    "password": "M*Y2Gm%xOS",
    "last_login": null,
    "is_superuser": false,
    "username": "Joan Francis",
    "first_name": "",
    "last_name": "",
    "email": "hortonkrista@example.com",
    "is_staff": false,
    "is_active": true,
    "date_joined": "2023-06-16T14:11:43.295Z",
    "groups": [],
    "user_permissions": []
  }
},
{
  "model": "auth.user",
  "pk": 152,
  "fields": {
    "password": "!(hX8bS9G7",
    "last_login": null,
    "is_superuser": false,
    "username": "Christopher Sexton",
    "first_name": "",
    "last_name": "",
    "email": "randalldustin@example.net",
    "is_staff": false,
    "is_active": true,
    "date_joined": "2023-06-16T14:11:43.295Z",
    "groups": [],
    "user_permissions": []
  }
},
{
  "model": "auth.user",
  "pk": 153,
  "fields": {
    "password": "_@0TnN6zy4",
    "last_login": null,
    "is_superuser": false,
    "username": "Dustin Shelton",
    "first_name": "",
    "last_name": "",
    "email": "eric34@example.com",
    "is_staff": false,
    "is_active": true,
    "date_joined": "2023-06-16T14:12:00.582Z",
    "groups": [],
    "user_permissions": []
  }
},
{
  "model": "auth.user",
  "pk": 154,
  "fields": {
    "password": "+i*QB(Lj_2",
    "last_login": null,
    "is_superuser": false,
    "username": "Brittany Smith",
    "first_name": "",
    "last_name": "",
    "email": "kristineholmes@example.com",
    "is_staff": false,
    "is_active": true,
    "date_joined": "2023-06-16T14:12:00.583Z",
    "groups": [],
    "user_permissions": []
  }
},
{
  "model": "auth.user",
  "pk": 155,
  "fields": {
    "password": "x^#6PT)qBw",
    "last_login": null,
    "is_superuser": false,
    "username": "Calvin Russell",
    "first_name": "",
    "last_name": "",
    "email": "alyssanelson@example.org",
    "is_staff": false,
    "is_active": true,
    "date_joined": "2023-06-16T14:12:00.583Z",
    "groups": [],
    "user_permissions": []
  }
},
{
  "model": "auth.user",
  "pk": 156,
  "fields": {
    "password": "3m)3A_wB#u",
    "last_login": null,
    "is_superuser": false,
    "username": "Marie Watson",
    "first_name": "",
    "last_name": "",
    "email": "todd79@example.com",
    "is_staff": false,
    "is_active": true,
    "date_joined": "2023-06-16T14:18:44.636Z",
    "groups": [],
    "user_permissions": []
  }
},
{
  "model": "auth.user",
  "pk": 157,
  "fields": {
    "password": "2eNO+Pt)+g",
    "last_login": null,
    "is_superuser": false,
    "username": "Jennifer Johnson",
    "first_name": "",
    "last_name": "",
    "email": "rtaylor@example.com",
    "is_staff": false,
    "is_active": true,
    "date_joined": "2023-06-16T14:18:44.636Z",
    "groups": [],
    "user_permissions": []
  }
},
{
  "model": "auth.user",
  "pk": 158,
  "fields": {
    "password": "@Vx9OAceYa",
    "last_login": null,
    "is_superuser": false,
    "username": "Adrian Carpenter",
    "first_name": "",
    "last_name": "",
    "email": "justinmartinez@example.com",
    "is_staff": false,
    "is_active": true,
    "date_joined": "2023-06-16T14:18:44.637Z",
    "groups": [],
    "user_permissions": []
  }
},
{
  "model": "auth.user",
  "pk": 159,
  "fields": {
    "password": "^9SaQnBh7v",
    "last_login": null,
    "is_superuser": false,
    "username": "Matthew Carroll",
    "first_name": "",
    "last_name": "",
    "email": "sharon59@example.org",
    "is_staff": false,
    "is_active": true,
    "date_joined": "2023-06-16T14:19:02.135Z",
    "groups": [],
    "user_permissions": []
  }
},
{
  "model": "auth.user",
  "pk": 163,
  "fields": {
    "password": "@HKlTQlyl6",
    "last_login": null,
    "is_superuser": false,
    "username": "Martha Buchanan",
    "first_name": "",
    "last_name": "",
    "email": "robert82@example.org",
    "is_staff": false,
    "is_active": true,
    "date_joined": "2023-06-16T14:19:02.136Z",
    "groups": [],
    "user_permissions": []
  }
},
{
  "model": "auth.user",
  "pk": 164,
  "fields": {
    "password": "$j*7K(tvM7",
    "last_login": null,
    "is_superuser": false,
    "username": "Eric Ramos DDS",
    "first_name": "",
    "last_name": "",
    "email": "zjohnson@example.net",
    "is_staff": false,
    "is_active": true,
    "date_joined": "2023-06-16T14:19:02.137Z",
    "groups": [],
    "user_permissions": []
  }
},
{
  "model": "auth.user",
  "pk": 165,
  "fields": {
    "password": "_BE8M76ozp",
    "last_login": null,
    "is_superuser": false,
    "username": "John Baxter",
    "first_name": "",
    "last_name": "",
    "email": "william34@example.com",
    "is_staff": false,
    "is_active": true,
    "date_joined": "2023-06-16T14:19:02.137Z",
    "groups": [],
    "user_permissions": []
  }
},
{
  "model": "auth.user",
  "pk": 166,
  "fields": {
    "password": "#&6ij*Dze&",
    "last_login": null,
    "is_superuser": false,
    "username": "Antonio Clarke",
    "first_name": "",
    "last_name": "",
    "email": "velasquezmarc@example.org",
    "is_staff": false,
    "is_active": true,
    "date_joined": "2023-06-16T14:19:02.138Z",
    "groups": [],
    "user_permissions": []
  }
},
{
  "model": "auth.user",
  "pk": 167,
  "fields": {
    "password": "7&#fJvL1^2",
    "last_login": null,
    "is_superuser": false,
    "username": "Matthew Clark",
    "first_name": "",
    "last_name": "",
    "email": "joelreynolds@example.com",
    "is_staff": false,
    "is_active": true,
    "date_joined": "2023-06-16T14:19:02.138Z",
    "groups": [],
    "user_permissions": []
  }
},
{
  "model": "auth.user",
  "pk": 168,
  "fields": {
    "password": "@5GAiiMeI8",
    "last_login": null,
    "is_superuser": false,
    "username": "Dennis Martinez",
    "first_name": "",
    "last_name": "",
    "email": "jonesscott@example.net",
    "is_staff": false,
    "is_active": true,
    "date_joined": "2023-06-16T14:21:25.703Z",
    "groups": [],
    "user_permissions": []
  }
},
{
  "model": "auth.user",
  "pk": 169,
  "fields": {
    "password": "uW7BJjyw^2",
    "last_login": null,
    "is_superuser": false,
    "username": "Teresa Obrien",
    "first_name": "",
    "last_name": "",
    "email": "johnsonjeffrey@example.org",
    "is_staff": false,
    "is_active": true,
    "date_joined": "2023-06-16T14:21:25.704Z",
    "groups": [],
    "user_permissions": []
  }
},
{
  "model": "auth.user",
  "pk": 170,
  "fields": {
    "password": "&7YfZP6YZp",
    "last_login": null,
    "is_superuser": false,
    "username": "Katrina Brown",
    "first_name": "",
    "last_name": "",
    "email": "joseph03@example.net",
    "is_staff": false,
    "is_active": true,
    "date_joined": "2023-06-16T14:21:25.704Z",
    "groups": [],
    "user_permissions": []
  }
},
{
  "model": "auth.user",
  "pk": 171,
  "fields": {
    "password": "m3GKpX4T&2",
    "last_login": null,
    "is_superuser": false,
    "username": "James Cooley",
    "first_name": "",
    "last_name": "",
    "email": "janet82@example.net",
    "is_staff": false,
    "is_active": true,
    "date_joined": "2023-06-16T14:21:25.704Z",
    "groups": [],
    "user_permissions": []
  }
},
{
  "model": "auth.user",
  "pk": 172,
  "fields": {
    "password": "7%U2WmYWvB",
    "last_login": null,
    "is_superuser": false,
    "username": "Derrick Baker",
    "first_name": "",
    "last_name": "",
    "email": "rachelbrown@example.net",
    "is_staff": false,
    "is_active": true,
    "date_joined": "2023-06-16T14:21:25.705Z",
    "groups": [],
    "user_permissions": []
  }
},
{
  "model": "auth.user",
  "pk": 173,
  "fields": {
    "password": "l$7gFkc%4o",
    "last_login": null,
    "is_superuser": false,
    "username": "Matthew Garrett",
    "first_name": "",
    "last_name": "",
    "email": "nsalazar@example.net",
    "is_staff": false,
    "is_active": true,
    "date_joined": "2023-06-16T14:21:25.705Z",
    "groups": [],
    "user_permissions": []
  }
},
{
  "model": "auth.user",
  "pk": 174,
  "fields": {
    "password": "9!1R%Tx+6F",
    "last_login": null,
    "is_superuser": false,
    "username": "Antonio Jackson",
    "first_name": "",
    "last_name": "",
    "email": "mcconnellsarah@example.com",
    "is_staff": false,
    "is_active": true,
    "date_joined": "2023-06-16T14:21:25.705Z",
    "groups": [],
    "user_permissions": []
  }
},
{
  "model": "auth.user",
  "pk": 175,
  "fields": {
    "password": "l_k5fAwMZ_",
    "last_login": null,
    "is_superuser": false,
    "username": "Stephanie Ortiz",
    "first_name": "",
    "last_name": "",
    "email": "martinezbrandon@example.org",
    "is_staff": false,
    "is_active": true,
    "date_joined": "2023-06-16T14:21:25.706Z",
    "groups": [],
    "user_permissions": []
  }
},
{
  "model": "auth.user",
  "pk": 176,
  "fields": {
    "password": "Y+P3vKBw&V",
    "last_login": null,
    "is_superuser": false,
    "username": "Christopher Knapp",
    "first_name": "",
    "last_name": "",
    "email": "ctaylor@example.com",
    "is_staff": false,
    "is_active": true,
    "date_joined": "2023-06-16T14:21:25.706Z",
    "groups": [],
    "user_permissions": []
  }
},
{
  "model": "auth.user",
  "pk": 177,
  "fields": {
    "password": "#EhT@yt#J4",
    "last_login": null,
    "is_superuser": false,
    "username": "Kathleen Ibarra",
    "first_name": "",
    "last_name": "",
    "email": "raymondgarcia@example.net",
    "is_staff": false,
    "is_active": true,
    "date_joined": "2023-06-16T14:21:25.707Z",
    "groups": [],
    "user_permissions": []
  }
},
{
  "model": "contenttypes.contenttype",
  "pk": 1,
  "fields": {
    "app_label": "admin",
    "model": "logentry"
  }
},
{
  "model": "contenttypes.contenttype",
  "pk": 2,
  "fields": {
    "app_label": "auth",
    "model": "permission"
  }
},
{
  "model": "contenttypes.contenttype",
  "pk": 3,
  "fields": {
    "app_label": "auth",
    "model": "group"
  }
},
{
  "model": "contenttypes.contenttype",
  "pk": 4,
  "fields": {
    "app_label": "auth",
    "model": "user"
  }
},
{
  "model": "contenttypes.contenttype",
  "pk": 5,
  "fields": {
    "app_label": "contenttypes",
    "model": "contenttype"
  }
},
{
  "model": "contenttypes.contenttype",
  "pk": 6,
  "fields": {
    "app_label": "sessions",
    "model": "session"
  }
},
{
  "model": "sessions.session",
  "pk": "nqvlh5hm7mhrwxutkifkdtd8umlh7qd1",
  "fields": {
    "session_data": ".eJxVjEEOwiAQRe_C2pDpdCrg0n3PQGAGpGpoUtqV8e7apAvd_vfefykftrX4raXFT6IuCkmdfscY-JHqTuQe6m3WPNd1maLeFX3QpsdZ0vN6uH8HJbTyra1jB1EMgB3Y8HAWShYhRUbqsQNLnHtEjgAkmaMTAmfIdZiEcu_U-wP4Hzei:1qA3uQ:bP_BOSSOboKRmxBok2OWV-SZEa09kjSWWS6A3RS9GBw",
    "expire_date": "2023-06-30T07:30:14.164Z"
  }
}
]
